CPP/__init__.py
CPP/Network/__init__.py
CPP/Server/__init__.py
CPP/_for/__init__.py
CPP/app/__init__.py
CPP/binary_lib/__init__.py
CPP/documentation/__init__.py
CPP/vector/__init__.py
C_C_Py-0.0.2.dist-info/METADATA
C_C_Py-0.0.2.dist-info/WHEEL
C_C_Py-0.0.2.dist-info/top_level.txt
C_C_Py-0.0.2.dist-info/RECORD
