Metadata-Version: 2.1
Name: C-C-Py
Version: 0.0.2
Summary: A big C++ Based python library instructions...to run type 'import CPP' twice use the 'CPP.doc()' function for info! 
Home-page: https://google.com
Author: FeedFall8
Author-email: FeedFall8@gmail.com
License: UNKNOWN
Platform: UNKNOWN
Classifier: Programming Language :: Python :: 3
Classifier: License :: OSI Approved :: MIT License
Classifier: Operating System :: OS Independent
Requires-Python: >=3.6
